dnastack/__init__.py
dnastack/__main__.py
dnastack/alpha/__init__.py
dnastack/alpha/app/__init__.py
dnastack/alpha/app/explorer.py
dnastack/alpha/app/workbench.py
dnastack/alpha/cli/__init__.py
dnastack/alpha/cli/auth.py
dnastack/alpha/cli/collections.py
dnastack/alpha/cli/commands.py
dnastack/alpha/cli/data_connect.py
dnastack/alpha/cli/wes.py
dnastack/alpha/cli/workbench/__init__.py
dnastack/alpha/cli/workbench/commands.py
dnastack/alpha/cli/workbench/engines_commands.py
dnastack/alpha/cli/workbench/utils.py
dnastack/alpha/cli/workbench/workflows_commands.py
dnastack/alpha/cli/workflow_param_parser.py
dnastack/alpha/client/__init__.py
dnastack/alpha/client/collections/__init__.py
dnastack/alpha/client/collections/client.py
dnastack/alpha/client/wes/__init__.py
dnastack/alpha/client/wes/client.py
dnastack/alpha/client/workbench/__init__.py
dnastack/alpha/client/workbench/base_client.py
dnastack/alpha/client/workbench/models.py
dnastack/alpha/client/workflow/__init__.py
dnastack/alpha/client/workflow/client.py
dnastack/alpha/client/workflow/models.py
dnastack/alpha/client/workflow/utils.py
dnastack/cli/__init__.py
dnastack/cli/auth/__init__.py
dnastack/cli/auth/command.py
dnastack/cli/auth/event_handlers.py
dnastack/cli/collections.py
dnastack/cli/config/__init__.py
dnastack/cli/config/commands.py
dnastack/cli/config/context.py
dnastack/cli/config/endpoints.py
dnastack/cli/config/service_registry.py
dnastack/cli/data_connect/__init__.py
dnastack/cli/data_connect/commands.py
dnastack/cli/data_connect/helper.py
dnastack/cli/drs.py
dnastack/cli/helpers/__init__.py
dnastack/cli/helpers/client_factory.py
dnastack/cli/helpers/command/__init__.py
dnastack/cli/helpers/command/decorator.py
dnastack/cli/helpers/command/group.py
dnastack/cli/helpers/command/spec.py
dnastack/cli/helpers/exporter.py
dnastack/cli/helpers/iterator_printer.py
dnastack/cli/helpers/printer.py
dnastack/cli/workbench/__init__.py
dnastack/cli/workbench/commands.py
amin_dnastack-0.1.0.dist-info/entry_points.txt
amin_dnastack-0.1.0.dist-info/METADATA
amin_dnastack-0.1.0.dist-info/WHEEL
amin_dnastack-0.1.0.dist-info/RECORD
